about/__init__.py
about/main.py
pnu_about-1.1.5.data/data/man/man1/about.1.gz
pnu_about-1.1.5.dist-info/License
pnu_about-1.1.5.dist-info/METADATA
pnu_about-1.1.5.dist-info/WHEEL
pnu_about-1.1.5.dist-info/entry_points.txt
pnu_about-1.1.5.dist-info/top_level.txt
pnu_about-1.1.5.dist-info/RECORD
